HakObserverLinuxpy/HakObserverLinuxpy.py
HakObserverLinuxpy/__init__.py
HakObserverLinuxpy-2.2.3.dist-info/METADATA
HakObserverLinuxpy-2.2.3.dist-info/WHEEL
HakObserverLinuxpy-2.2.3.dist-info/top_level.txt
HakObserverLinuxpy-2.2.3.dist-info/RECORD
